autopass.py
autopass-0.14.dist-info/METADATA
autopass-0.14.dist-info/WHEEL
autopass-0.14.dist-info/licenses/LICENSE
autopass-0.14.dist-info/RECORD
