Metadata-Version: 2.4
Name: autopass
Version: 0.14
Summary: Entering password automatically for sudo, ssh and scp
Project-URL: homepage, https://github.com/xinlin-z/autopass
Author: xinlin-z
License: MIT License
License-File: LICENSE
Keywords: password,scp,ssh,sshpass,sudo
Classifier: License :: OSI Approved :: MIT License
Classifier: Operating System :: POSIX
Classifier: Programming Language :: Python :: 3
Requires-Python: >=3.8
